{"name":"Check Infomation LG","id":"practice;check-infomation-lg","testSteps":[{"number":1,"description":"1: Check Infomation LG ({url\u003dhttps://wwwstg.lg.com/vn/shop/addtocartsimulator/page/index, product\u003dMD05849136, country\u003dvn})","duration":0,"startTime":"2023-11-03T17:36:46.694+07:00[Asia/Bangkok]","precondition":false,"level":0,"lineNumber":15,"children":[{"number":2,"description":"Given Auto open url https://wwwstg.lg.com/vn/shop/addtocartsimulator/page/index","duration":23323,"startTime":"2023-11-03T17:36:46.768+07:00[Asia/Bangkok]","screenshots":[{"screenshot":"fc11e05b495e47d30d777961375f2ad3eeea56481af6708d0f9392293e4befae.png","timeStamp":1699007830091}],"result":"SUCCESS","precondition":false,"level":1,"children":[{"number":3,"description":"Open url https://wwwstg.lg.com/vn/shop/addtocartsimulator/page/index","duration":22984,"startTime":"2023-11-03T17:36:47.099+07:00[Asia/Bangkok]","screenshots":[{"screenshot":"fc11e05b495e47d30d777961375f2ad3eeea56481af6708d0f9392293e4befae.png","timeStamp":1699007830083}],"result":"SUCCESS","precondition":false,"level":2,"children":[{"number":4,"description":"Auto opens the https://wwwstg.lg.com/vn/shop/addtocartsimulator/page/index","duration":22962,"startTime":"2023-11-03T17:36:47.109+07:00[Asia/Bangkok]","screenshots":[{"screenshot":"fc11e05b495e47d30d777961375f2ad3eeea56481af6708d0f9392293e4befae.png","timeStamp":1699007830071}],"result":"SUCCESS","precondition":false,"level":3}]}]},{"number":5,"description":"When Add product \"MD05849136\" To Cart And Go To Cart","duration":26620,"startTime":"2023-11-03T17:37:10.092+07:00[Asia/Bangkok]","screenshots":[{"screenshot":"34ba5dbba69f09960b80407586999e704aca392bbbce8e33e8ace06e8566ae55.png","timeStamp":1699007856712}],"result":"SUCCESS","precondition":false,"level":1,"children":[{"number":6,"description":"Auto enters \u0027MD05849136\u0027 into Product_ID_Input","duration":281,"startTime":"2023-11-03T17:37:10.194+07:00[Asia/Bangkok]","screenshots":[{"screenshot":"c452bb5dbbabc13aa17b5e6f00bbed921f0ad935519df3a5e5a6baa3a993defc.png","timeStamp":1699007830475}],"result":"SUCCESS","precondition":false,"level":2},{"number":7,"description":"Auto clicks on Add_To_Cart_Btn","duration":11141,"startTime":"2023-11-03T17:37:10.528+07:00[Asia/Bangkok]","screenshots":[{"screenshot":"fc11e05b495e47d30d777961375f2ad3eeea56481af6708d0f9392293e4befae.png","timeStamp":1699007841669}],"result":"SUCCESS","precondition":false,"level":2},{"number":8,"description":"Auto clicks on Go_To_Cart_Btn","duration":11950,"startTime":"2023-11-03T17:37:24.757+07:00[Asia/Bangkok]","screenshots":[{"screenshot":"34ba5dbba69f09960b80407586999e704aca392bbbce8e33e8ace06e8566ae55.png","timeStamp":1699007856707}],"result":"SUCCESS","precondition":false,"level":2}]},{"number":9,"description":"When Get Infomation In Cart","duration":31002,"startTime":"2023-11-03T17:37:36.713+07:00[Asia/Bangkok]","screenshots":[{"screenshot":"87e07c3c41520d501f79ce2f52b25246f1f0785ebd78fa5b9f080c5a8f6c8bc8.png","timeStamp":1699007887715}],"result":"SUCCESS","precondition":false,"level":1,"children":[{"number":10,"description":"Auto should see NameProductInCart that is displayed","duration":1370,"startTime":"2023-11-03T17:37:37.833+07:00[Asia/Bangkok]","screenshots":[{"screenshot":"c648c132b222e735eea9ca0b0e0b1fc21f8ff325bd30f9b75809785f76572734.png","timeStamp":1699007859203}],"result":"SUCCESS","reportData":[{"title":"Text of NameProductInCart","contents":"LG Inverter Linear™ Tủ lạnh ngăn đá trên với DoorCooling+™ (Đen) GN-L702GB","isEvidence":false,"id":"report-data-07505e47-49a4-4372-a9eb-2755ba733409"}],"precondition":false,"level":2},{"number":11,"description":"Auto should see PricePriductInCart that is displayed","duration":491,"startTime":"2023-11-03T17:37:40.842+07:00[Asia/Bangkok]","screenshots":[{"screenshot":"e5c73402a244046bdaaa2b830ecbc2f797e2176ece16abbbcb991b96f63e86c8.png","timeStamp":1699007861333}],"result":"SUCCESS","reportData":[{"title":"Text of PricePriductInCart","contents":"14.990.000 ₫","isEvidence":false,"id":"report-data-771b46a1-4302-4ad2-8bc2-0e4bcfee838d"}],"precondition":false,"level":2},{"number":12,"description":"Auto selects #value in Select_Qty_Product","duration":5753,"startTime":"2023-11-03T17:37:41.378+07:00[Asia/Bangkok]","screenshots":[{"screenshot":"0a029f6914fdf79a8968382c106be2966f6ce3721314cb81bd2f5cc083bd9ebe.png","timeStamp":1699007867131}],"result":"SUCCESS","precondition":false,"level":2},{"number":13,"description":"Auto clicks on ThanhToanBtn","duration":15446,"startTime":"2023-11-03T17:37:52.266+07:00[Asia/Bangkok]","screenshots":[{"screenshot":"87e07c3c41520d501f79ce2f52b25246f1f0785ebd78fa5b9f080c5a8f6c8bc8.png","timeStamp":1699007887711}],"result":"SUCCESS","precondition":false,"level":2}]},{"number":14,"description":"When Enter Information In Check Out Page \"vn\"","duration":23713,"startTime":"2023-11-03T17:38:07.716+07:00[Asia/Bangkok]","exception":{"errorType":"java.lang.AssertionError","message":"\r\nExpected: an element that is visible\r\n     but: no matching element found by not so","stackTrace":[{"declaringClass":"screenplay.actions.ActionCommon","methodName":"typeText","fileName":"ActionCommon.java","lineNumber":34},{"declaringClass":"smartosc.page.CheckOutPage","methodName":"enterInformation","fileName":"CheckOutPage.java","lineNumber":35},{"declaringClass":"io.cucumber.java.Invoker","methodName":"doInvoke","fileName":"Invoker.java","lineNumber":66},{"declaringClass":"io.cucumber.java.Invoker","methodName":"invoke","fileName":"Invoker.java","lineNumber":24},{"declaringClass":"io.cucumber.java.AbstractGlueDefinition","methodName":"invokeMethod","fileName":"AbstractGlueDefinition.java","lineNumber":47},{"declaringClass":"io.cucumber.java.JavaStepDefinition","methodName":"execute","fileName":"JavaStepDefinition.java","lineNumber":29},{"declaringClass":"io.cucumber.core.runner.CoreStepDefinition","methodName":"execute","fileName":"CoreStepDefinition.java","lineNumber":66},{"declaringClass":"io.cucumber.core.runner.PickleStepDefinitionMatch","methodName":"runStep","fileName":"PickleStepDefinitionMatch.java","lineNumber":63},{"declaringClass":"io.cucumber.core.runner.TestStep","methodName":"executeStep","fileName":"TestStep.java","lineNumber":86},{"declaringClass":"io.cucumber.core.runner.TestStep","methodName":"run","fileName":"TestStep.java","lineNumber":57},{"declaringClass":"io.cucumber.core.runner.PickleStepTestStep","methodName":"run","fileName":"PickleStepTestStep.java","lineNumber":51},{"declaringClass":"io.cucumber.core.runner.TestCase","methodName":"run","fileName":"TestCase.java","lineNumber":95},{"declaringClass":"io.cucumber.core.runner.Runner","methodName":"runPickle","fileName":"Runner.java","lineNumber":75},{"declaringClass":"io.cucumber.core.runtime.CucumberExecutionContext","methodName":"lambda$runTestCase$3","fileName":"CucumberExecutionContext.java","lineNumber":151},{"declaringClass":"io.cucumber.core.runtime.RethrowingThrowableCollector","methodName":"executeAndThrow","fileName":"RethrowingThrowableCollector.java","lineNumber":23},{"declaringClass":"io.cucumber.core.runtime.CucumberExecutionContext","methodName":"runTestCase","fileName":"CucumberExecutionContext.java","lineNumber":151},{"declaringClass":"io.cucumber.junit.FeatureRunner","methodName":"runChild","fileName":"FeatureRunner.java","lineNumber":144},{"declaringClass":"io.cucumber.junit.FeatureRunner","methodName":"runChild","fileName":"FeatureRunner.java","lineNumber":28},{"declaringClass":"io.cucumber.junit.FeatureRunner","methodName":"run","fileName":"FeatureRunner.java","lineNumber":137},{"declaringClass":"io.cucumber.junit.CucumberSerenityRunner","methodName":"runChild","fileName":"CucumberSerenityRunner.java","lineNumber":259},{"declaringClass":"io.cucumber.junit.CucumberSerenityRunner","methodName":"runChild","fileName":"CucumberSerenityRunner.java","lineNumber":58}]},"result":"FAILURE","precondition":false,"level":1,"children":[{"number":15,"description":"Auto enters \u0027havietdung10@gmail.com\u0027 into EmailInput","duration":717,"startTime":"2023-11-03T17:38:07.767+07:00[Asia/Bangkok]","screenshots":[{"screenshot":"729c53fd0df3326a0a89d1316c9dffdd0da80b6427c7699fdedb60845679f2cc.png","timeStamp":1699007888484}],"result":"SUCCESS","precondition":false,"level":2},{"number":16,"description":"Auto enters \u0027dung\u0027 into FirstInput","duration":282,"startTime":"2023-11-03T17:38:08.531+07:00[Asia/Bangkok]","screenshots":[{"screenshot":"36f32a85f406e340a0038af98d03d577f39c4c76cc79c5d8f9824a8aa4b56d4d.png","timeStamp":1699007888813}],"result":"SUCCESS","precondition":false,"level":2},{"number":17,"description":"Auto enters \u0027ha\u0027 into LastName","duration":245,"startTime":"2023-11-03T17:38:08.858+07:00[Asia/Bangkok]","screenshots":[{"screenshot":"0d500d3aa6abe0f4f119e941c734088ba18e21b24f98b63b52bdc96bfedfec25.png","timeStamp":1699007889103}],"result":"SUCCESS","precondition":false,"level":2},{"number":18,"description":"Auto enters \u0027236 khuong dinh\u0027 into AddressInput","duration":346,"startTime":"2023-11-03T17:38:09.156+07:00[Asia/Bangkok]","screenshots":[{"screenshot":"3568355a19984d4df0cd66574ef94fe2aa8b7f0a415d2a46aae115083e1b7fb1.png","timeStamp":1699007889502}],"result":"SUCCESS","precondition":false,"level":2},{"number":19,"description":"Auto selects #value in ProvinceInput","duration":301,"startTime":"2023-11-03T17:38:14.540+07:00[Asia/Bangkok]","screenshots":[{"screenshot":"756b9d500d1b3490ccdf194538660cb169a9a94d89a948d81c399a5b4291e00f.png","timeStamp":1699007894841}],"result":"SUCCESS","precondition":false,"level":2},{"number":20,"description":"Auto selects #value in DistrictInput","duration":251,"startTime":"2023-11-03T17:38:14.857+07:00[Asia/Bangkok]","screenshots":[{"screenshot":"72691f665eb5063c5008e769c2e293e8bd54766b0ec37028270de638d3af483a.png","timeStamp":1699007895108}],"result":"SUCCESS","precondition":false,"level":2},{"number":21,"description":"Auto enters \u00270835678910\u0027 into PhoneNumberInput","duration":302,"startTime":"2023-11-03T17:38:15.156+07:00[Asia/Bangkok]","screenshots":[{"screenshot":"74029b229e6c16de2510688f8e1549a4ebbd77951188a7dfa5bf1cd90c4a41a1.png","timeStamp":1699007895458}],"result":"SUCCESS","precondition":false,"level":2},{"number":22,"description":"Auto clicks on ContinueButton","duration":385,"startTime":"2023-11-03T17:38:20.504+07:00[Asia/Bangkok]","screenshots":[{"screenshot":"1f6239f0e30e7fe29a9241af40c83a4043481f1aec96a9cb254356de5c640fff.png","timeStamp":1699007900889}],"result":"SUCCESS","precondition":false,"level":2},{"number":23,"description":"Auto enters \u0027havietdung10@gmail.com\u0027 into EmailInput","duration":325,"startTime":"2023-11-03T17:38:20.934+07:00[Asia/Bangkok]","screenshots":[{"screenshot":"d084af8a46f1734995cefcf12fa59184eb906f4c8a8d351c3a6c840ca7374db7.png","timeStamp":1699007901259}],"result":"SUCCESS","precondition":false,"level":2}]}]},{"number":24,"description":"Type text: name, 123","duration":0,"startTime":"2023-11-03T17:38:32.345+07:00[Asia/Bangkok]","exception":{"errorType":"java.lang.AssertionError","message":"\r\nExpected: an element that is visible\r\n     but: no matching element found by not so","stackTrace":[{"declaringClass":"screenplay.actions.ActionCommon","methodName":"typeText","fileName":"ActionCommon.java","lineNumber":34},{"declaringClass":"smartosc.page.CheckOutPage","methodName":"enterInformation","fileName":"CheckOutPage.java","lineNumber":35},{"declaringClass":"io.cucumber.java.Invoker","methodName":"doInvoke","fileName":"Invoker.java","lineNumber":66},{"declaringClass":"io.cucumber.java.Invoker","methodName":"invoke","fileName":"Invoker.java","lineNumber":24},{"declaringClass":"io.cucumber.java.AbstractGlueDefinition","methodName":"invokeMethod","fileName":"AbstractGlueDefinition.java","lineNumber":47},{"declaringClass":"io.cucumber.java.JavaStepDefinition","methodName":"execute","fileName":"JavaStepDefinition.java","lineNumber":29},{"declaringClass":"io.cucumber.core.runner.CoreStepDefinition","methodName":"execute","fileName":"CoreStepDefinition.java","lineNumber":66},{"declaringClass":"io.cucumber.core.runner.PickleStepDefinitionMatch","methodName":"runStep","fileName":"PickleStepDefinitionMatch.java","lineNumber":63},{"declaringClass":"io.cucumber.core.runner.TestStep","methodName":"executeStep","fileName":"TestStep.java","lineNumber":86},{"declaringClass":"io.cucumber.core.runner.TestStep","methodName":"run","fileName":"TestStep.java","lineNumber":57},{"declaringClass":"io.cucumber.core.runner.PickleStepTestStep","methodName":"run","fileName":"PickleStepTestStep.java","lineNumber":51},{"declaringClass":"io.cucumber.core.runner.TestCase","methodName":"run","fileName":"TestCase.java","lineNumber":95},{"declaringClass":"io.cucumber.core.runner.Runner","methodName":"runPickle","fileName":"Runner.java","lineNumber":75},{"declaringClass":"io.cucumber.core.runtime.CucumberExecutionContext","methodName":"lambda$runTestCase$3","fileName":"CucumberExecutionContext.java","lineNumber":151},{"declaringClass":"io.cucumber.core.runtime.RethrowingThrowableCollector","methodName":"executeAndThrow","fileName":"RethrowingThrowableCollector.java","lineNumber":23},{"declaringClass":"io.cucumber.core.runtime.CucumberExecutionContext","methodName":"runTestCase","fileName":"CucumberExecutionContext.java","lineNumber":151},{"declaringClass":"io.cucumber.junit.FeatureRunner","methodName":"runChild","fileName":"FeatureRunner.java","lineNumber":144},{"declaringClass":"io.cucumber.junit.FeatureRunner","methodName":"runChild","fileName":"FeatureRunner.java","lineNumber":28},{"declaringClass":"io.cucumber.junit.FeatureRunner","methodName":"run","fileName":"FeatureRunner.java","lineNumber":137},{"declaringClass":"io.cucumber.junit.CucumberSerenityRunner","methodName":"runChild","fileName":"CucumberSerenityRunner.java","lineNumber":259},{"declaringClass":"io.cucumber.junit.CucumberSerenityRunner","methodName":"runChild","fileName":"CucumberSerenityRunner.java","lineNumber":58}]},"result":"FAILURE","precondition":false,"level":0},{"number":25,"description":"When Get Infomation In CheckOut","duration":16,"startTime":"2023-11-03T17:38:32.345+07:00[Asia/Bangkok]","result":"SKIPPED","precondition":false,"level":0},{"number":26,"description":"Then Compare Price And Qty","duration":0,"startTime":"2023-11-03T17:38:32.361+07:00[Asia/Bangkok]","result":"SKIPPED","precondition":false,"level":0},{"number":27,"description":"When Select Payment Method","duration":0,"startTime":"2023-11-03T17:38:32.361+07:00[Asia/Bangkok]","result":"SKIPPED","precondition":false,"level":0}],"userStory":{"id":"practice","storyName":"practice","displayName":"practice","path":"testcase3/testcase3.feature","type":"feature"},"featureTag":{"name":"Testcase3/practice","type":"feature","displayName":"Testcase3/practice"},"title":"Check Infomation LG","description":"","tags":[{"name":"Testcase3","type":"capability","displayName":"Testcase3"},{"name":"testcase3_vn","type":"tag","displayName":"testcase3_vn"},{"name":"Testcase3/practice","type":"feature","displayName":"practice"}],"startTime":"2023-11-03T17:36:46.569+07:00[Asia/Bangkok]","duration":105807,"testFailureCause":{"errorType":"java.lang.AssertionError","message":"\r\nExpected: an element that is visible\r\n     but: no matching element found by not so","stackTrace":[{"declaringClass":"screenplay.actions.ActionCommon","methodName":"typeText","fileName":"ActionCommon.java","lineNumber":34},{"declaringClass":"smartosc.page.CheckOutPage","methodName":"enterInformation","fileName":"CheckOutPage.java","lineNumber":35},{"declaringClass":"io.cucumber.java.Invoker","methodName":"doInvoke","fileName":"Invoker.java","lineNumber":66},{"declaringClass":"io.cucumber.java.Invoker","methodName":"invoke","fileName":"Invoker.java","lineNumber":24},{"declaringClass":"io.cucumber.java.AbstractGlueDefinition","methodName":"invokeMethod","fileName":"AbstractGlueDefinition.java","lineNumber":47},{"declaringClass":"io.cucumber.java.JavaStepDefinition","methodName":"execute","fileName":"JavaStepDefinition.java","lineNumber":29},{"declaringClass":"io.cucumber.core.runner.CoreStepDefinition","methodName":"execute","fileName":"CoreStepDefinition.java","lineNumber":66},{"declaringClass":"io.cucumber.core.runner.PickleStepDefinitionMatch","methodName":"runStep","fileName":"PickleStepDefinitionMatch.java","lineNumber":63},{"declaringClass":"io.cucumber.core.runner.TestStep","methodName":"executeStep","fileName":"TestStep.java","lineNumber":86},{"declaringClass":"io.cucumber.core.runner.TestStep","methodName":"run","fileName":"TestStep.java","lineNumber":57},{"declaringClass":"io.cucumber.core.runner.PickleStepTestStep","methodName":"run","fileName":"PickleStepTestStep.java","lineNumber":51},{"declaringClass":"io.cucumber.core.runner.TestCase","methodName":"run","fileName":"TestCase.java","lineNumber":95},{"declaringClass":"io.cucumber.core.runner.Runner","methodName":"runPickle","fileName":"Runner.java","lineNumber":75},{"declaringClass":"io.cucumber.core.runtime.CucumberExecutionContext","methodName":"lambda$runTestCase$3","fileName":"CucumberExecutionContext.java","lineNumber":151},{"declaringClass":"io.cucumber.core.runtime.RethrowingThrowableCollector","methodName":"executeAndThrow","fileName":"RethrowingThrowableCollector.java","lineNumber":23},{"declaringClass":"io.cucumber.core.runtime.CucumberExecutionContext","methodName":"runTestCase","fileName":"CucumberExecutionContext.java","lineNumber":151},{"declaringClass":"io.cucumber.junit.FeatureRunner","methodName":"runChild","fileName":"FeatureRunner.java","lineNumber":144},{"declaringClass":"io.cucumber.junit.FeatureRunner","methodName":"runChild","fileName":"FeatureRunner.java","lineNumber":28},{"declaringClass":"io.cucumber.junit.FeatureRunner","methodName":"run","fileName":"FeatureRunner.java","lineNumber":137},{"declaringClass":"io.cucumber.junit.CucumberSerenityRunner","methodName":"runChild","fileName":"CucumberSerenityRunner.java","lineNumber":259},{"declaringClass":"io.cucumber.junit.CucumberSerenityRunner","methodName":"runChild","fileName":"CucumberSerenityRunner.java","lineNumber":58}]},"testFailureClassname":"java.lang.AssertionError","testFailureMessage":"\r\nExpected: an element that is visible\r\n     but: no matching element found by not so","testFailureSummary":"FAILURE;java.lang.AssertionError;\r\nExpected: an element that is visible\r\n     but: no matching element found by not so;ActionCommon.java","projectKey":"","annotatedResult":"FAILURE","sessionId":"c89f3037ec77aea19d56664b5e00db7d","driver":"chrome:auto","isManualTestingUpToDate":false,"dataTable":{"headers":["url","product","country"],"rows":[{"values":["https://wwwstg.lg.com/vn/shop/addtocartsimulator/page/index","MD05849136","vn"],"lineNumber":15,"result":"FAILURE"}],"predefinedRows":true,"scenarioOutline":"Given Auto open url \u003curl\u003e\n\rWhen Add product \"\u003cproduct\u003e\" To Cart And Go To Cart\n\rWhen Get Infomation In Cart\n\rWhen Enter Information In Check Out Page \"\u003ccountry\u003e\"\n\rWhen Get Infomation In CheckOut\n\rThen Compare Price And Qty\n\rWhen Select Payment Method\n\r","dataSetDescriptors":[{"startRow":0,"rowCount":0,"name":"","description":""}]},"manual":false,"testSource":"Cucumber","actors":[{"name":"Auto","can":["browse the web"]}],"result":"FAILURE","scenarioOutline":"Given Auto open url \u003curl\u003e\r\nWhen Add product \"\u003cproduct\u003e\" To Cart And Go To Cart\r\nWhen Get Infomation In Cart\r\nWhen Enter Information In Check Out Page \"\u003ccountry\u003e\"\r\nWhen Get Infomation In CheckOut\r\nThen Compare Price And Qty\r\nWhen Select Payment Method"}